cow_face/__init__.py
cow_face/cow_face.py
cow_face-1.0.1.dist-info/METADATA
cow_face-1.0.1.dist-info/WHEEL
cow_face-1.0.1.dist-info/top_level.txt
cow_face-1.0.1.dist-info/RECORD
