Metadata-Version: 2.1
Name: cow_face
Version: 1.0.1
Summary: Add a cow mask to the face
Home-page: https://github.com/SinaHosseini/Cow-Face
Author: Sina Hosseini
Author-email: sshosseinivaez@gmail.com
License: UNKNOWN
Platform: UNKNOWN
